taskgroup/__init__.py
taskgroup/install.py
taskgroup/py.typed
taskgroup/runners.py
taskgroup/taskgroups.py
taskgroup/tasks.py
taskgroup/timeouts.py
taskgroup-0.2.0.dist-info/LICENSE
taskgroup-0.2.0.dist-info/WHEEL
taskgroup-0.2.0.dist-info/METADATA
taskgroup-0.2.0.dist-info/RECORD
